WeiXueyuanShejimoshiJiaocheng/README.md
WeiXueyuanShejimoshiJiaocheng/__init__.py
WeiXueyuanShejimoshiJiaocheng/__main__.py
WeiXueyuanShejimoshiJiaocheng/file.epub
WeiXueyuanShejimoshiJiaocheng/index.html
WeiXueyuanShejimoshiJiaocheng/css/__init__.py
WeiXueyuanShejimoshiJiaocheng/css/annotations.css
WeiXueyuanShejimoshiJiaocheng/css/main.css
WeiXueyuanShejimoshiJiaocheng/css/normalize.css
WeiXueyuanShejimoshiJiaocheng/css/popup.css
WeiXueyuanShejimoshiJiaocheng/font/__init__.py
WeiXueyuanShejimoshiJiaocheng/font/fontello.eot
WeiXueyuanShejimoshiJiaocheng/font/fontello.svg
WeiXueyuanShejimoshiJiaocheng/font/fontello.ttf
WeiXueyuanShejimoshiJiaocheng/font/fontello.woff
WeiXueyuanShejimoshiJiaocheng/img/__init__.py
WeiXueyuanShejimoshiJiaocheng/img/annotator-glyph-sprite.png
WeiXueyuanShejimoshiJiaocheng/img/annotator-icon-sprite.png
WeiXueyuanShejimoshiJiaocheng/img/apple-touch-icon.png
WeiXueyuanShejimoshiJiaocheng/img/cancelfullscreen.png
WeiXueyuanShejimoshiJiaocheng/img/close.png
WeiXueyuanShejimoshiJiaocheng/img/fullscreen.png
WeiXueyuanShejimoshiJiaocheng/img/loader.gif
WeiXueyuanShejimoshiJiaocheng/img/menu-icon.png
WeiXueyuanShejimoshiJiaocheng/img/save.png
WeiXueyuanShejimoshiJiaocheng/img/saved.png
WeiXueyuanShejimoshiJiaocheng/img/settings-s.png
WeiXueyuanShejimoshiJiaocheng/img/settings.png
WeiXueyuanShejimoshiJiaocheng/img/star.png
WeiXueyuanShejimoshiJiaocheng/js/__init__.py
WeiXueyuanShejimoshiJiaocheng/js/epub.js
WeiXueyuanShejimoshiJiaocheng/js/epub.min.js
WeiXueyuanShejimoshiJiaocheng/js/epub.min.map
WeiXueyuanShejimoshiJiaocheng/js/hooks.min.js
WeiXueyuanShejimoshiJiaocheng/js/hooks.min.map
WeiXueyuanShejimoshiJiaocheng/js/reader.js
WeiXueyuanShejimoshiJiaocheng/js/reader.js.map
WeiXueyuanShejimoshiJiaocheng/js/reader.min.js
WeiXueyuanShejimoshiJiaocheng/js/reader.min.map
WeiXueyuanShejimoshiJiaocheng/js/hooks/__init__.py
WeiXueyuanShejimoshiJiaocheng/js/hooks/extensions/__init__.py
WeiXueyuanShejimoshiJiaocheng/js/hooks/extensions/highlight.js
wei_xueyuan_shejimoshi_jiaocheng-2024.3.2.0.dist-info/METADATA
wei_xueyuan_shejimoshi_jiaocheng-2024.3.2.0.dist-info/WHEEL
wei_xueyuan_shejimoshi_jiaocheng-2024.3.2.0.dist-info/entry_points.txt
wei_xueyuan_shejimoshi_jiaocheng-2024.3.2.0.dist-info/top_level.txt
wei_xueyuan_shejimoshi_jiaocheng-2024.3.2.0.dist-info/RECORD
